{"cameraMode":{"drawMode":0,"name":"Shaded","section":"Shading Mode"},"sceneLighting":true,"audioPlay":false,"sceneViewState":{"m_AlwaysRefresh":false,"showFog":true,"showSkybox":true,"showFlares":true,"showImageEffects":true,"showParticleSystems":true,"showVisualEffectGraphs":true,"m_FxEnabled":true},"in2DMode":false,"pivot":{"x":1.0951164960861207,"y":-0.4132317900657654,"z":0.4721032977104187},"rotation":{"x":-0.21517367660999299,"y":-0.755306601524353,"z":0.3002001643180847,"w":-0.5413824319839478},"size":128.81332397460938,"orthographic":false}